scanner/cli.py
scanner/config.py
scanner/file_utils.py
scanner/output.py
scanner/run_code_scanner.py
scanner/scan.py
scanner/project_typings/cli_args.py
scanner/project_typings/config_data.py
scanner/project_typings/scan_data.py
t4wefan_code_scanner-0.1.3.dist-info/METADATA
t4wefan_code_scanner-0.1.3.dist-info/WHEEL
t4wefan_code_scanner-0.1.3.dist-info/entry_points.txt
t4wefan_code_scanner-0.1.3.dist-info/top_level.txt
t4wefan_code_scanner-0.1.3.dist-info/RECORD
